Metadata-Version: 2.1
Name: cfm-tiptapy
Version: 0.15.3
Summary: Library that generates HTML output from JSON export of tiptap editor
Home-page: https://github.com/Clever-fm/tiptapy
Author: Alex Santos
Author-email: anewmanvs@gmail.com
License: http://www.opensource.org/licenses/mit-license.php
Platform: UNKNOWN
Classifier: Programming Language :: Python :: 3
Classifier: License :: OSI Approved :: MIT License
Classifier: Operating System :: OS Independent
License-File: LICENSE
